__init__.py
revit_meows.py
revit_meows-0.1.7.dist-info/METADATA
revit_meows-0.1.7.dist-info/WHEEL
revit_meows-0.1.7.dist-info/top_level.txt
revit_meows-0.1.7.dist-info/RECORD
