Metadata-Version: 2.2
Name: revit_meows
Version: 0.1.7
Summary: A tool for extracting data from Revit ACC
Home-page: https://github.com/chuongmep/revit-meows
Author: chuongmep
Author-email: chuongpqvn@gmail.com
Classifier: Programming Language :: Python :: 3
Classifier: License :: OSI Approved :: Apache Software License
Classifier: Operating System :: OS Independent
Requires-Python: >=3.9
Requires-Dist: pandas>=2.1.4
Requires-Dist: numpy>=1.26.0
Requires-Dist: requests>=2.0
Requires-Dist: aps-toolkit
Dynamic: author
Dynamic: author-email
Dynamic: classifier
Dynamic: description
Dynamic: description-content-type
Dynamic: home-page
Dynamic: requires-dist
Dynamic: requires-python
Dynamic: summary
